hardle/__init__.py
hardle/__main__.py
hardle/download.py
hardle-0.1.2.dist-info/entry_points.txt
hardle-0.1.2.dist-info/LICENSE
hardle-0.1.2.dist-info/WHEEL
hardle-0.1.2.dist-info/METADATA
hardle-0.1.2.dist-info/RECORD
